GestUniDt/GestUniDt.py
GestUniDt/__init__.py
GestUniDt-1.0.3.dist-info/LICENSE
GestUniDt-1.0.3.dist-info/METADATA
GestUniDt-1.0.3.dist-info/WHEEL
GestUniDt-1.0.3.dist-info/top_level.txt
GestUniDt-1.0.3.dist-info/RECORD
