Metadata-Version: 2.2
Name: GestUniDt
Version: 1.0.3
Summary: A Python library quickly store and fetch different types of data.
Home-page: https://github.com/eaannist/GestUniDt
Author: eaannist
Author-email: eaannist@gmail.com
Classifier: Programming Language :: Python :: 3
Classifier: Operating System :: OS Independent
Requires-Python: >=3.7
License-File: LICENSE
Requires-Dist: pandas
Dynamic: author
Dynamic: author-email
Dynamic: classifier
Dynamic: description
Dynamic: description-content-type
Dynamic: home-page
Dynamic: requires-dist
Dynamic: requires-python
Dynamic: summary
